{
  "siteTheme": {
    "ui": "classic",
    "paletteId": "Arcane",
    "kineticFont": "default"
  },
  "entries": [
    {
      "id": "20260318-224158-h599",
      "title": "Zaldunarenn",
      "commanders": [
        "Zaldunarenn"
      ],
      "dateStart": "2026-03-18T21:41:58.000Z",
      "dateEnd": "2026-03-18T23:02:24.000Z",
      "dateLabel": "18/3/2026, 22:41:58 - 19/3/2026, 0:02:24",
      "url": "https://Imacardio.github.io/chuichui/?report=20260318-224158-h599",
      "summary": {
        "borderlandsPct": 0.03571428571428571,
        "mapSlices": [
          {
            "name": "Eternal Battlegrounds",
            "value": 27,
            "color": "#ffffff"
          },
          {
            "name": "Blue Borderlands",
            "value": 1,
            "color": "#3b82f6"
          }
        ],
        "avgSquadSize": 16,
        "avgEnemySize": 34
      }
    },
    {
      "id": "20260317-225258-rgr0",
      "title": "Breissingr, Bronky Ambulancia, Zaldunarenn",
      "commanders": [
        "Breissingr",
        "Bronky Ambulancia",
        "Zaldunarenn"
      ],
      "dateStart": "2026-03-17T21:52:58.000Z",
      "dateEnd": "2026-03-17T22:41:48.000Z",
      "dateLabel": "17/3/2026, 22:52:58 - 17/3/2026, 23:41:48",
      "url": "https://Imacardio.github.io/chuichui/?report=20260317-225258-rgr0",
      "summary": {
        "borderlandsPct": 0.7272727272727273,
        "mapSlices": [
          {
            "name": "Red Borderlands",
            "value": 8,
            "color": "#ef4444"
          },
          {
            "name": "Eternal Battlegrounds",
            "value": 3,
            "color": "#ffffff"
          }
        ],
        "avgSquadSize": 18,
        "avgEnemySize": 37
      }
    },
    {
      "id": "20260316-222201-1aew",
      "title": "Bronky Ambulancia",
      "commanders": [
        "Bronky Ambulancia"
      ],
      "dateStart": "2026-03-16T21:22:01.000Z",
      "dateEnd": "2026-03-16T23:00:42.000Z",
      "dateLabel": "16/3/2026, 22:22:01 - 17/3/2026, 0:00:42",
      "url": "https://Imacardio.github.io/chuichui/?report=20260316-222201-1aew",
      "summary": {
        "borderlandsPct": 0,
        "mapSlices": [
          {
            "name": "Eternal Battlegrounds",
            "value": 22,
            "color": "#ffffff"
          }
        ],
        "avgSquadSize": 23,
        "avgEnemySize": 60
      }
    },
    {
      "id": "20260315-222125-mjus",
      "title": "Masnuelinx",
      "commanders": [
        "Masnuelinx"
      ],
      "dateStart": "2026-03-15T21:21:25.000Z",
      "dateEnd": "2026-03-15T22:52:14.000Z",
      "dateLabel": "15/3/2026, 22:21:25 - 15/3/2026, 23:52:14",
      "url": "https://Imacardio.github.io/chuichui/?report=20260315-222125-mjus",
      "summary": {
        "borderlandsPct": 0.6,
        "mapSlices": [
          {
            "name": "Red Borderlands",
            "value": 6,
            "color": "#ef4444"
          },
          {
            "name": "Eternal Battlegrounds",
            "value": 4,
            "color": "#ffffff"
          }
        ],
        "avgSquadSize": 15,
        "avgEnemySize": 43
      }
    },
    {
      "id": "20260309-223733-84jo",
      "title": "Bronky Ambulancia",
      "commanders": [
        "Bronky Ambulancia"
      ],
      "dateStart": "2026-03-09T21:37:33.000Z",
      "dateEnd": "2026-03-09T22:53:31.000Z",
      "dateLabel": "9/3/2026, 22:37:33 - 9/3/2026, 23:53:31",
      "url": "https://Imacardio.github.io/chuichui/?report=20260309-223733-84jo",
      "summary": {
        "borderlandsPct": 0.1875,
        "mapSlices": [
          {
            "name": "Eternal Battlegrounds",
            "value": 13,
            "color": "#ffffff"
          },
          {
            "name": "Red Borderlands",
            "value": 3,
            "color": "#ef4444"
          }
        ],
        "avgSquadSize": 20,
        "avgEnemySize": 42
      }
    },
    {
      "id": "20260309-223733-gnoj",
      "title": "Bronky Ambulancia",
      "commanders": [
        "Bronky Ambulancia"
      ],
      "dateStart": "2026-03-09T21:37:33.000Z",
      "dateEnd": "2026-03-09T22:53:31.000Z",
      "dateLabel": "9/3/2026, 22:37:33 - 9/3/2026, 23:53:31",
      "url": "https://Imacardio.github.io/chuichui/?report=20260309-223733-gnoj",
      "summary": {
        "borderlandsPct": 0.1875,
        "mapSlices": [
          {
            "name": "Eternal Battlegrounds",
            "value": 13,
            "color": "#ffffff"
          },
          {
            "name": "Red Borderlands",
            "value": 3,
            "color": "#ef4444"
          }
        ],
        "avgSquadSize": 20,
        "avgEnemySize": 42
      }
    },
    {
      "id": "20260308-222828-ci27",
      "title": "Masnuelinx",
      "commanders": [
        "Masnuelinx"
      ],
      "dateStart": "2026-03-08T21:28:28.000Z",
      "dateEnd": "2026-03-08T22:56:16.000Z",
      "dateLabel": "8/3/2026, 22:28:28 - 8/3/2026, 23:56:16",
      "url": "https://Imacardio.github.io/chuichui/?report=20260308-222828-ci27",
      "summary": {
        "borderlandsPct": 0,
        "mapSlices": [
          {
            "name": "Eternal Battlegrounds",
            "value": 16,
            "color": "#ffffff"
          }
        ],
        "avgSquadSize": 21,
        "avgEnemySize": 36
      }
    },
    {
      "id": "20260308-223007-93yw",
      "title": "Masnuelinx",
      "commanders": [
        "Masnuelinx"
      ],
      "dateStart": "2026-03-08T21:30:07.000Z",
      "dateEnd": "2026-03-08T21:38:39.000Z",
      "dateLabel": "8/3/2026, 22:30:07 - 8/3/2026, 22:38:39",
      "url": "https://Imacardio.github.io/chuichui/?report=20260308-223007-93yw",
      "summary": {
        "borderlandsPct": 0,
        "mapSlices": [
          {
            "name": "Eternal Battlegrounds",
            "value": 1,
            "color": "#ffffff"
          }
        ],
        "avgSquadSize": 19,
        "avgEnemySize": 0
      }
    },
    {
      "id": "20260305-223515-ukpa",
      "title": "Zaldunarenn",
      "commanders": [
        "Zaldunarenn"
      ],
      "dateStart": "2026-03-05T21:35:15.000Z",
      "dateEnd": "2026-03-05T23:00:02.000Z",
      "dateLabel": "5/3/2026, 22:35:15 - 6/3/2026, 0:00:02",
      "url": "https://Imacardio.github.io/chuichui/?report=20260305-223515-ukpa",
      "summary": {
        "borderlandsPct": 0,
        "mapSlices": [
          {
            "name": "Eternal Battlegrounds",
            "value": 15,
            "color": "#ffffff"
          }
        ],
        "avgSquadSize": 12,
        "avgEnemySize": 33
      }
    },
    {
      "id": "20260305-223515-0v1u",
      "title": "Zaldunarenn",
      "commanders": [
        "Zaldunarenn"
      ],
      "dateStart": "2026-03-05T21:35:15.000Z",
      "dateEnd": "2026-03-05T23:00:02.000Z",
      "dateLabel": "5/3/2026, 22:35:15 - 6/3/2026, 0:00:02",
      "url": "https://Imacardio.github.io/chuichui/?report=20260305-223515-0v1u",
      "summary": {
        "borderlandsPct": 0,
        "mapSlices": [
          {
            "name": "Eternal Battlegrounds",
            "value": 15,
            "color": "#ffffff"
          }
        ],
        "avgSquadSize": 12,
        "avgEnemySize": 33
      }
    },
    {
      "id": "20260304-222625-lqc2",
      "title": "Bronky Ambulancia",
      "commanders": [
        "Bronky Ambulancia"
      ],
      "dateStart": "2026-03-04T21:26:25.000Z",
      "dateEnd": "2026-03-04T22:59:53.000Z",
      "dateLabel": "4/3/2026, 22:26:25 - 4/3/2026, 23:59:53",
      "url": "https://Imacardio.github.io/chuichui/?report=20260304-222625-lqc2",
      "summary": {
        "borderlandsPct": 0.1111111111111111,
        "mapSlices": [
          {
            "name": "Eternal Battlegrounds",
            "value": 16,
            "color": "#ffffff"
          },
          {
            "name": "Blue Borderlands",
            "value": 2,
            "color": "#3b82f6"
          }
        ],
        "avgSquadSize": 14,
        "avgEnemySize": 37
      }
    },
    {
      "id": "20260303-223011-6dcl",
      "title": "Masnuelinn, Masnuelinx",
      "commanders": [
        "Masnuelinn",
        "Masnuelinx"
      ],
      "dateStart": "2026-03-03T21:30:11.000Z",
      "dateEnd": "2026-03-03T22:55:31.000Z",
      "dateLabel": "3/3/2026, 22:30:11 - 3/3/2026, 23:55:31",
      "url": "https://Imacardio.github.io/chuichui/?report=20260303-223011-6dcl",
      "summary": {
        "borderlandsPct": 1,
        "mapSlices": [
          {
            "name": "Red Borderlands",
            "value": 12,
            "color": "#ef4444"
          },
          {
            "name": "Blue Borderlands",
            "value": 1,
            "color": "#3b82f6"
          }
        ],
        "avgSquadSize": 18,
        "avgEnemySize": 37
      }
    },
    {
      "id": "20260303-223011-cm73",
      "title": "Masnuelinn, Masnuelinx",
      "commanders": [
        "Masnuelinn",
        "Masnuelinx"
      ],
      "dateStart": "2026-03-03T21:30:11.000Z",
      "dateEnd": "2026-03-03T22:55:31.000Z",
      "dateLabel": "3/3/2026, 22:30:11 - 3/3/2026, 23:55:31",
      "url": "https://Imacardio.github.io/chuichui/?report=20260303-223011-cm73",
      "summary": {
        "borderlandsPct": 1,
        "mapSlices": [
          {
            "name": "Red Borderlands",
            "value": 12,
            "color": "#ef4444"
          },
          {
            "name": "Blue Borderlands",
            "value": 1,
            "color": "#3b82f6"
          }
        ],
        "avgSquadSize": 18,
        "avgEnemySize": 37
      }
    },
    {
      "id": "20260302-221543-w3dd",
      "title": "I Bronky I",
      "commanders": [
        "I Bronky I"
      ],
      "dateStart": "2026-03-02T21:15:43.000Z",
      "dateEnd": "2026-03-02T22:45:02.000Z",
      "dateLabel": "2/3/2026, 22:15:43 - 2/3/2026, 23:45:02",
      "url": "https://Imacardio.github.io/chuichui/?report=20260302-221543-w3dd",
      "summary": {
        "borderlandsPct": 0.6486486486486487,
        "mapSlices": [
          {
            "name": "Eternal Battlegrounds",
            "value": 13,
            "color": "#ffffff"
          },
          {
            "name": "Blue Borderlands",
            "value": 12,
            "color": "#3b82f6"
          },
          {
            "name": "Red Borderlands",
            "value": 12,
            "color": "#ef4444"
          }
        ],
        "avgSquadSize": 20,
        "avgEnemySize": 14
      }
    }
  ]
}